imagingcontrol4/.gitignore
imagingcontrol4/__init__.py
imagingcontrol4/bufferpool.py
imagingcontrol4/devenum.py
imagingcontrol4/display.py
imagingcontrol4/error.py
imagingcontrol4/grabber.py
imagingcontrol4/gui.py
imagingcontrol4/helper.py
imagingcontrol4/ic4exception.py
imagingcontrol4/imagebuffer.py
imagingcontrol4/imagetype.py
imagingcontrol4/libic4core.so
imagingcontrol4/libic4plugin_display_generic_opengl.so
imagingcontrol4/libic4plugin_video_linux_h26x.so
imagingcontrol4/library.py
imagingcontrol4/native.py
imagingcontrol4/native_gui.py
imagingcontrol4/propconstants.py
imagingcontrol4/properties.py
imagingcontrol4/py.typed
imagingcontrol4/queuesink.py
imagingcontrol4/sink.py
imagingcontrol4/snapsink.py
imagingcontrol4/videowriter.py
imagingcontrol4/pyside6/__init__.py
imagingcontrol4/pyside6/dialogs.py
imagingcontrol4/pyside6/display.py
imagingcontrol4-1.4.0.3240.dist-info/METADATA
imagingcontrol4-1.4.0.3240.dist-info/WHEEL
imagingcontrol4-1.4.0.3240.dist-info/RECORD
