Metadata-Version: 2.1
Name: imagingcontrol4
Version: 1.4.0.3240
Summary: IC Imaging Control 4 Core Library
Author: The Imaging Source
Author-email: support@theimagingsource.com
License: IMAGING CONTROL END-USER LICENSE AGREEMENT
Keywords: SDK,camera,ic4,imagingcontrol,the imaging source
Classifier: Development Status :: 5 - Production/Stable
Classifier: Intended Audience :: Developers
Classifier: Intended Audience :: Information Technology
Classifier: Intended Audience :: Manufacturing
Classifier: Intended Audience :: Other Audience
Classifier: Intended Audience :: Science/Research
Classifier: License :: Other/Proprietary License
Classifier: Operating System :: Microsoft :: Windows
Classifier: Operating System :: POSIX :: Linux
Classifier: Programming Language :: Python :: 3
Classifier: Topic :: Multimedia :: Graphics :: Capture
Classifier: Topic :: Multimedia :: Graphics :: Capture :: Digital Camera
Classifier: Topic :: Multimedia :: Video :: Capture
Classifier: Topic :: Scientific/Engineering :: Image Processing
Classifier: Topic :: Software Development
Classifier: Topic :: Software Development :: Libraries
Requires-Python: >=3.8
Provides-Extra: numpy
Requires-Dist: numpy; extra == 'numpy'
Provides-Extra: pyside6
Requires-Dist: imagingcontrol4pyside6; extra == 'pyside6'
